Metadata-Version: 2.1
Name: weasel
Version: 0.4.0
Summary: Weasel: A small and easy workflow system
Home-page: https://github.com/explosion/weasel/
Author: Explosion
Author-email: contact@explosion.ai
License: MIT
Project-URL: Release notes, https://github.com/explosion/weasel/releases
Project-URL: Source, https://github.com/explosion/weasel/
Classifier: Environment :: Console
Classifier: Intended Audience :: Developers
Classifier: Intended Audience :: Science/Research
Classifier: License :: OSI Approved :: MIT License
Classifier: Operating System :: POSIX :: Linux
Classifier: Operating System :: MacOS :: MacOS X
Classifier: Operating System :: Microsoft :: Windows
Classifier: Programming Language :: Python :: 3
Classifier: Programming Language :: Python :: 3.7
Classifier: Programming Language :: Python :: 3.8
Classifier: Programming Language :: Python :: 3.9
Classifier: Programming Language :: Python :: 3.10
Classifier: Programming Language :: Python :: 3.11
Classifier: Programming Language :: Python :: 3.12
Classifier: Topic :: Scientific/Engineering
Requires-Python: >=3.7
License-File: LICENSE
Requires-Dist: confection <0.2.0,>=0.0.4
Requires-Dist: packaging >=20.0
Requires-Dist: wasabi <1.2.0,>=0.9.1
Requires-Dist: srsly <3.0.0,>=2.4.3
Requires-Dist: typer <0.10.0,>=0.3.0
Requires-Dist: cloudpathlib <1.0.0,>=0.7.0
Requires-Dist: smart-open <8.0.0,>=5.2.1
Requires-Dist: requests <3.0.0,>=2.13.0
Requires-Dist: pydantic !=1.8,!=1.8.1,<3.0.0,>=1.7.4
